Lab3Count_0-f/design.vhd
LIBRARY IEEE;
USE IEEE.std_logic_1164.ALL;
USE IEEE.numeric_std.ALL;

ENTITY CNT16 IS
    GENERIC (N : INTEGER := 4);
    PORT (
        CLK, ARESETN : IN STD_LOGIC;
        LOAD : IN STD_LOGIC;
        DIR : IN STD_LOGIC;
        TCEN : IN STD_LOGIC;
        CNTEN : IN STD_LOGIC;
        PRE : IN STD_LOGIC_VECTOR (N-1 DOWNTO 0);
        TC : OUT STD_LOGIC;
        CNT : OUT STD_LOGIC_VECTOR(N-1 DOWNTO 0)
    );
END ENTITY CNT16;


ARCHITECTURE PROC_2 OF CNT16 IS
    -- declare count value and next count value
    SIGNAL Q, Q_next : unsigned(N
    - 1 DOWNTO 0);
BEGIN
    -- state register for the count value
    P_REG : PROCESS (CLK, ARESETN)
    BEGIN
        IF ARESETN = '0' THEN
            Q <= (OTHERS => '0') AFTER 5 ns;
        ELSIF CLK'event AND CLK = '1' THEN
            Q <= Q_NEXT AFTER 5 ns;
        END IF;
    END PROCESS P_REG;
    P_COMB : PROCESS (Q, DIR, CNTEN, TCEN, LOAD, PRE)
 
        -- declare terminal count values (TC)
        VARIABLE MAXVAL : unsigned (N - 1 DOWNTO 0);
        VARIABLE MINVAL : unsigned (N - 1 DOWNTO 0);
    BEGIN
        MAXVAL := (OTHERS => '1');
        MINVAL := (OTHERS => '0');
        -- default output values
        Q_NEXT <= Q AFTER 5 ns;
        TC <= '0' AFTER 5 ns;
        -- next state logic
        IF LOAD = '1' THEN
            Q_NEXT <= unsigned(PRE) AFTER 5 ns;
        ELSIF CNTEN = '0' THEN
            IF DIR = '1' THEN
                Q_NEXT <= Q + 1 AFTER 5 ns;
            ELSE
                Q_NEXT <= Q - 1 AFTER 5 ns;
            END IF;
        END IF;
        -- set TC (active low)
        IF (TCEN = '1') AND ((DIR = '1' AND Q = MAXVAL) OR (DIR = '0'
            AND Q(N - 1 DOWNTO 0) = MINVAL)) THEN
            TC <= '1' AFTER 5 ns;
        END IF;
    END PROCESS P_COMB;
    CNT <= STD_LOGIC_VECTOR(Q);
END ARCHITECTURE PROC_2;

Lab3Count_0-f/testbench.vhd


-- Code your testbench here
LIBRARY IEEE;
USE IEEE.std_logic_1164.ALL;

ENTITY CNT16_TB IS
    GENERIC (N : INTEGER := 4);
END CNT16_TB;

ARCHITECTURE SIM OF CNT16_TB IS
    -- DUT component
    COMPONENT CNT16 IS
         PORT (
            CLK, ARESETN : IN STD_LOGIC;
            LOAD : IN STD_LOGIC;
            DIR : IN STD_LOGIC;
            TCEN : IN STD_LOGIC;
            CNTEN : IN STD_LOGIC;
            PRE : IN STD_LOGIC_VECTOR (N-1 DOWNTO 0);
            TC : OUT STD_LOGIC;
            CNT : OUT STD_LOGIC_VECTOR(N-1 DOWNTO 0)
    	);
    END COMPONENT;
    --signals
    constant ClockFrequency : integer := 25e6; -- 25 MHz
    CONSTANT CLK_PERIOD : TIME := 1000 ms / ClockFrequency; -- clock period (20 MHz)
    SIGNAL PRE, CNT : STD_LOGIC_VECTOR (N-1 DOWNTO 0) := (OTHERS => '0');
    SIGNAL ARESETN, LOAD, DIR, TCEN, CNTEN, TC : STD_LOGIC := '0';
    SIGNAL CLK : STD_LOGIC := '0';
BEGIN
	-- CLK <= not CLK after CLK_PERIOD;
    
    --mapping port
    DUT : CNT16
    PORT MAP(CLK, ARESETN,LOAD,DIR,TCEN,CNTEN,PRE,TC,CNT);
    PROCESS
    BEGIN
     
  		
       wait;
    END PROCESS;
END SIM;

Lab3Count_0-f/dump.vcd
$date
	Thu Jul 27 07:42:59 2023
$end
$version
	QuestaSim Version 2021.3
$end
$timescale
	1ns
$end

$scope module cnt16_tb $end
$var wire 1 ! ARESETN $end
$var wire 1 " CLK $end
$var wire 1 # LOAD $end
$var wire 1 $ PRE [3] $end
$var wire 1 % PRE [2] $end
$var wire 1 & PRE [1] $end
$var wire 1 ' PRE [0] $end
$var wire 1 ( TCEN $end
$var wire 1 ) CNTEN $end
$var wire 1 * DIR $end
$var wire 1 + TC $end
$var wire 1 , CNT [3] $end
$var wire 1 - CNT [2] $end
$var wire 1 . CNT [1] $end
$var wire 1 / CNT [0] $end
$upscope $end
$enddefinitions $end
#0
$dumpvars
1!
0#
0*
1(
1)
x+
0"
0$
0%
0&
0'
x,
x-
x.
x/
$end
#5
0+
0!
0/
0.
0-
0,
#10
1+
#20
1"
#40
1!
0)
0(
1*
0"
#45
0+
#60
1"
#65
1/
#80
0"
#100
1"
#105
0/
1.
#120
0"
#140
1"
#145
1/
#160
0"
#180
1"
#185
0/
0.
1-
#200
0"
#220
1"
#225
1/
#240
0"
#260
1"
#265
0/
1.
#280
0"
#300
1"
#305
1/
#320
0"
#340
1"
#345
0/
0.
0-
1,
#360
0"
#380
1"
#385
1/
#400
0"
#420
1"
#425
0/
1.
#440
0"
#460
1"
#465
1/
#480
0"
#500
1"
#505
0/
0.
1-
#520
0"
#540
1"
#545
1/
#560
0"
#580
1"
#585
0/
1.
#600
0"
#620
1"
#625
1/
#640
0"
#660
1"
#665
0/
0.
0-
0,
#680
0"
#690
1#
1$
1%
1&
1'
#700
1"
#705
1/
1.
1-
1,
#720
0"
#730
0#
0*
#740
1"
#745
0/
#760
0"
#780
1"
#785
1/
0.
#800
0"
#820
1"
#825
0/
#840
0"
#860
1"
#865
1/
1.
0-
#880
0"
#900
1"
#905
0/
#920
0"
#940
1"
#945
1/
0.
#960
0"
#980
1"
#985
0/
#1000
0"
#1020
1"
#1025
1/
1.
1-
0,
#1040
0"
#1060
1"
#1065
0/
#1080
0"
#1100
1"
#1105
1/
0.
#1120
0"
#1140
1"
#1145
0/
#1160
0"
#1180
1"
#1185
1/
1.
0-
#1200
0"
#1220
1"
#1225
0/
#1240
0"
#1260
1"
#1265
1/
0.
#1280
0"
#1300
1"
#1305
0/
#1320
0"
#1340
1"
#1345
1/
1.
1-
1,
#1360
0"
#1380
1"
#1385
0/
#1400
0!
0"
#1405
0.
0-
0,
#1420
1"
#1440
0"
#1450
1!
1*
1#
#1460
1"
#1465
1/
1.
1-
1,
#1480
0"
#1500
1"
#1520
1(
0"
#1525
1+
#1540
1"
#1560
0(
0*
0$
0%
0&
0'
0"
#1565
0+
#1580
1"
#1585
0/
0.
0-
0,
#1600
0"
#1620
1"
#1640
1(
0"
#1645
1+
#1660
1"
#1680
0#
1*
0"
#1685
0+
#1700
1"
#1705
1/
#1720
0"
#1740
1"
#1745
0/
1.
#1760
1)
0"
#1780
1"
#1800
0"
#1820
1"
#1840
0)
0"
#1860
1"
#1865
1/
#1880
0"
#1900
1"
#1905
0/
0.
1-
#1920
0"
#1940
1"
#1945
1/
#1960
0*
0"
#1980
1"
#1985
0/
#2000
1#
1*
1$
1%
1&
1'
0"
#2020
1"
#2025
1/
1.
1,
#2030
1+
